retarget/__init__.py
retarget/__main__.py
retarget/install_isaacgym.py
retarget/third_party/__init__.py
retarget/third_party/isaacgym/__init__.py
retarget/third_party/poselib/__init__.py
retarget/third_party/poselib/poselib/__init__.py
retarget/third_party/poselib/poselib/core/__init__.py
retarget/third_party/poselib/poselib/core/rotation3d.py
retarget/third_party/poselib/poselib/core/tensor_utils.py
retarget/third_party/poselib/poselib/core/backend/__init__.py
retarget/third_party/poselib/poselib/core/backend/abstract.py
retarget/third_party/poselib/poselib/core/backend/logger.py
retarget/third_party/poselib/poselib/core/tests/__init__.py
retarget/third_party/poselib/poselib/core/tests/test_rotation.py
retarget/third_party/poselib/poselib/skeleton/__init__.py
retarget/third_party/poselib/poselib/skeleton/skeleton3d.py
retarget/third_party/poselib/poselib/skeleton/backend/__init__.py
retarget/third_party/poselib/poselib/skeleton/backend/fbx/FbxCommon.py
retarget/third_party/poselib/poselib/skeleton/backend/fbx/__init__.py
retarget/third_party/poselib/poselib/skeleton/backend/fbx/fbx_backend.py
retarget/third_party/poselib/poselib/skeleton/backend/fbx/fbx_read_wrapper.py
retarget/third_party/poselib/poselib/skeleton/tests/__init__.py
retarget/third_party/poselib/poselib/skeleton/tests/test_skeleton.py
retarget/third_party/poselib/poselib/skeleton/tests/transfer_npy.py
retarget/third_party/poselib/poselib/visualization/__init__.py
retarget/third_party/poselib/poselib/visualization/common.py
retarget/third_party/poselib/poselib/visualization/core.py
retarget/third_party/poselib/poselib/visualization/plt_plotter.py
retarget/third_party/poselib/poselib/visualization/simple_plotter_tasks.py
retarget/third_party/poselib/poselib/visualization/skeleton_plotter_tasks.py
retarget/third_party/poselib/poselib/visualization/tests/__init__.py
retarget/third_party/poselib/poselib/visualization/tests/test_plotter.py
retarget/utils/__init__.py
retarget/utils/dependency_checker.py
robot_retarget-0.1.3.dist-info/licenses/LICENSE
robot_retarget-0.1.3.dist-info/METADATA
robot_retarget-0.1.3.dist-info/WHEEL
robot_retarget-0.1.3.dist-info/entry_points.txt
robot_retarget-0.1.3.dist-info/top_level.txt
robot_retarget-0.1.3.dist-info/RECORD
